README.md
setup.py
src/fairytaler/__init__.py
src/fairytaler/__main__.py
src/fairytaler/hinting.py
src/fairytaler/pipeline.py
src/fairytaler.egg-info/PKG-INFO
src/fairytaler.egg-info/SOURCES.txt
src/fairytaler.egg-info/dependency_links.txt
src/fairytaler.egg-info/entry_points.txt
src/fairytaler.egg-info/requires.txt
src/fairytaler.egg-info/top_level.txt
src/fairytaler/architectures/__init__.py
src/fairytaler/architectures/dit.py
src/fairytaler/architectures/mmdit.py
src/fairytaler/blocks/__init__.py
src/fairytaler/blocks/conv.py
src/fairytaler/blocks/dit.py
src/fairytaler/embeddings/__init__.py
src/fairytaler/embeddings/audio.py
src/fairytaler/embeddings/position.py
src/fairytaler/embeddings/rotary.py
src/fairytaler/embeddings/text.py
src/fairytaler/embeddings/timestep.py
src/fairytaler/models/__init__.py
src/fairytaler/models/cfm.py
src/fairytaler/modules/__init__.py
src/fairytaler/modules/attention.py
src/fairytaler/modules/base.py
src/fairytaler/modules/feed_forward.py
src/fairytaler/modules/normalization.py
src/fairytaler/modules/audio/__init__.py
src/fairytaler/modules/audio/mel_spectrogram.py
src/fairytaler/util/__init__.py
src/fairytaler/util/config_util.py
src/fairytaler/util/introspection_util.py
src/fairytaler/util/log_util.py
src/fairytaler/util/mask_util.py
src/fairytaler/util/mixing_util.py
src/fairytaler/util/normalization_util.py
src/fairytaler/util/seed_util.py
src/fairytaler/util/string_util.py
src/fairytaler/util/terminal_util.py
src/fairytaler/util/transformer_util.py