Metadata-Version: 2.1
Name: fairytaler
Version: 0.1.1
Summary: An unofficial reimplementation of F5TTS
Home-page: https://github.com/painebenjamin/fairytaler
Author: Benjamin Paine
Author-email: painebenjamin@gmail.com
License: cc-by-nc-4.0
Classifier: Development Status :: 4 - Beta
Classifier: Intended Audience :: Developers
Classifier: Intended Audience :: Education
Classifier: Intended Audience :: Science/Research
Classifier: Operating System :: OS Independent
Classifier: Topic :: Scientific/Engineering :: Artificial Intelligence
Classifier: Programming Language :: Python :: 3
Classifier: Programming Language :: Python :: 3.8
Classifier: Programming Language :: Python :: 3.9
Classifier: Programming Language :: Python :: 3.10
Classifier: Programming Language :: Python :: 3.11
Classifier: Programming Language :: Python :: 3.12
Requires-Python: >=3.8.0
Requires-Dist: accelerate~=1.0
Requires-Dist: einops>=0.8
Requires-Dist: huggingface-hub~=0.26
Requires-Dist: librosa>=0.10
Requires-Dist: numpy~=1.22
Requires-Dist: pillow~=9.5
Requires-Dist: safetensors~=0.4
Requires-Dist: scipy>=1.11
Requires-Dist: scikit-learn~=1.5
Requires-Dist: torch>=2.4
Requires-Dist: torchaudio>=2.4
Requires-Dist: torchdiffeq~=0.2
Requires-Dist: torchvision>=0.19
Requires-Dist: transformers>=4.41
Requires-Dist: vocos~=0.1
